{"schema_version":1,"universe":"us-all","generated_at":"2026-07-24T17:45:29.436812+00:00","columns":["sym","close","dv20m","d_stage","w_stage","m_stage","w_conf","score","setup","near","rev"],"stats":{"scanned":96,"rows":70},"results":[["AAPL",332.98,18574.8,2,2,2,95,92,"B","r1",null],["ADM",86.32,245.6,2,2,2,95,92,"B","r1",null],["ACT",46.64,16.4,2,2,2,94,92,"B","r1",null],["ABBV",258.64,2138.6,2,2,2,88,87,"B","r1",null],["ACRS",5.31,11.1,2,2,2,95,85,"B","s1","TB"],["ADPT",22.49,62.8,2,2,2,95,77,"B","r1",null],["ACHV",6.16,13.6,2,2,2,93,77,"b","s1",null],["AAMI",80.97,34.5,2,2,2,95,74,"b","r1",null],["ABCB",87.3,47.1,2,2,2,84,73,"b","r1",null],["ACA",145.2,125.8,2,2,2,95,71,"b","s1",null],["ACHC",34.83,105.6,2,2,2,95,71,"B","r1",null],["ADC",80.92,80.7,2,2,2,84,70,"b","s1",null],["ACIW",56.22,62.3,2,2,2,95,70,"B","r1",null],["ACMR",86.25,141.3,2,2,2,91,67,"b","s1",null],["ABSI",7.73,49.9,2,2,2,91,67,"b","r1",null],["ABCL",5.49,48.7,2,2,2,91,67,"b","s1",null],["ABNB",141.38,490.8,3,2,2,78,66,"b","r1",null],["ACGL",102.36,175.3,3,2,2,84,65,"b","s1","T"],["AAL",14.42,2283.5,1,2,2,71,null,null,"s1",null],["ADI",370.9,1665.8,2,2,2,77,null,null,"r1",null],["ABT",103.39,1235.2,1,1,4,56,null,null,"r1",null],["ACN",145.58,1229.7,4,4,4,95,null,null,"r1",null],["ADBE",223.7,1229.4,4,4,4,94,null,null,"avwap5y",null],["AAOI",102.55,1092.8,1,1,2,42,null,null,"r1",null],["ADP",248.55,611.0,1,1,1,42,null,null,"r1","B"],["ADSK",206.99,486.3,4,4,4,94,null,null,"s1",null],["AA",44.87,316.3,1,4,1,71,null,null,"avwap5y",null],["A",139.08,303.3,3,3,2,60,null,null,"r1","TB"],["ABVX",128.65,249.0,3,2,2,74,null,null,"r1",null],["ACHR",4.95,171.4,4,4,4,95,null,null,"s1","B"],["ACI",11.04,120.3,4,4,4,95,null,null,"avwap5y",null],["AAON",104.86,112.6,2,1,2,56,null,null,"s1",null],["ACM",70.15,108.9,4,4,4,95,null,null,"s1",null],["AAP",54.4,101.5,2,2,2,77,null,null,"r1",null],["ACLS",136.21,87.6,2,2,2,87,null,null,"r1",null],["ABEV",3.09,63.5,2,2,2,84,null,null,"s1",null],["ADT",7.01,52.7,4,4,4,84,null,null,"r1",null],["ABG",226.42,52.1,3,3,3,60,null,null,"avwap5y",null],["ACAD",24.66,44.5,3,3,2,60,null,null,"r1",null],["ADEA",26.0,44.2,2,2,2,82,null,null,"s1",null],["ADMA",8.2,25.6,4,4,4,95,null,null,"s1","B"],["ACVA",7.66,23.7,1,1,1,42,null,null,"s1",null],["ABM",47.58,23.5,3,2,3,79,null,null,"s1","T"],["ADTN",10.07,23.2,1,1,1,58,null,null,"avwap5y",null],["ADNT",20.49,20.5,1,1,4,72,null,null,"r1",null],["ABR",5.06,19.8,4,4,4,95,null,null,"avwap5y",null],["ABTC",5.63,12.6,4,4,4,95,null,null,"avwap5y",null],["ABUS",4.41,12.3,3,3,3,42,null,null,"r1",null],["AAUC",21.16,11.8,1,4,1,64,null,null,"s1",null],["AD",35.09,10.2,4,4,4,95,null,null,"s1",null],["ABEO",6.11,9.9,2,2,3,82,null,null,"s1",null],["AAT",24.32,9.6,2,2,2,93,null,null,"s1",null],["ABAT",2.23,8.6,4,4,1,95,null,null,"s1",null],["ABX",10.61,8.6,2,2,2,93,null,null,"r1","B"],["ADAM",8.69,7.6,2,2,2,84,null,null,"s1","B"],["ACDC",4.35,6.6,1,1,1,58,null,null,"s1",null],["ACNB",62.63,5.0,2,2,2,95,null,null,null,null],["ACEL",12.03,4.1,3,2,2,71,null,null,"r1",null],["ACCO",4.01,3.4,3,2,3,83,null,null,"r1","T"],["ACIC",10.23,3.3,4,4,4,94,null,null,"s1",null],["AARD",6.34,3.2,4,4,null,94,null,null,"r1",null],["ACB",2.67,3.1,4,4,4,95,null,null,"r1",null],["ACP",5.11,2.5,1,4,4,79,null,null,"s1",null],["ACH",3.15,2.0,1,2,1,82,null,null,"s1",null],["ACRE",4.59,1.9,4,4,1,83,null,null,"s1",null],["ABOS",2.18,1.6,1,1,1,42,null,null,"avwap5y",null],["ADCT",1.2,1.5,4,4,4,95,null,null,"s1","B"],["ADAG",3.38,1.3,2,3,2,42,null,null,"s1",null],["ACNT",15.14,1.3,3,3,2,42,null,null,"s1",null],["ACTG",4.66,1.2,2,2,2,84,null,null,"s1","T"]]}